cuinixam_app_dev/__init__.py
cuinixam_app_dev/core/__init__.py
cuinixam_app_dev/core/cmd_line.py
cuinixam_app_dev/core/docs_utils.py
cuinixam_app_dev/core/exceptions.py
cuinixam_app_dev/core/logging.py
cuinixam_app_dev/core/runnable.py
cuinixam_app_dev/core/scoop_wrapper.py
cuinixam_app_dev/core/subprocess.py
cuinixam_app_dev/mvp/__init__.py
cuinixam_app_dev/mvp/event_manager.py
cuinixam_app_dev/mvp/presenter.py
cuinixam_app_dev/mvp/view.py
cuinixam_app_dev/py.typed
cuinixam_app_dev-0.1.1.dist-info/LICENSE
cuinixam_app_dev-0.1.1.dist-info/METADATA
cuinixam_app_dev-0.1.1.dist-info/WHEEL
cuinixam_app_dev-0.1.1.dist-info/RECORD
