Metadata-Version: 2.1
Name: cuinixam-app-dev
Version: 0.1.1
Summary: My application development modules.
Home-page: https://github.com/cuinixam/cuinixam-app-dev
License: MIT
Author: cuinixam
Author-email: me@cuinixam.com
Requires-Python: >=3.10,<4.0
Classifier: Development Status :: 2 - Pre-Alpha
Classifier: Intended Audience :: Developers
Classifier: License :: OSI Approved :: MIT License
Classifier: Natural Language :: English
Classifier: Operating System :: OS Independent
Classifier: Programming Language :: Python :: 3
Classifier: Programming Language :: Python :: 3.10
Classifier: Programming Language :: Python :: 3.11
Classifier: Topic :: Software Development :: Libraries
Requires-Dist: loguru (>=0.7.1,<0.8.0)
Requires-Dist: mashumaro (>=3.9.1,<4.0.0)
Project-URL: Bug Tracker, https://github.com/cuinixam/cuinixam-app-dev/issues
Project-URL: Changelog, https://github.com/cuinixam/cuinixam-app-dev/blob/main/CHANGELOG.md
Project-URL: Documentation, https://cuinixam-app-dev.readthedocs.io
Project-URL: Repository, https://github.com/cuinixam/cuinixam-app-dev
